{
  "metadata": {
    "generated_at": "2025-08-29T00:30:11.411706",
    "script_version": "1.0.0",
    "total_recommendations": 6
  },
  "summary": {
    "by_priority": {
      "CRÍTICA": 1,
      "ALTA": 2,
      "MÉDIA": 3,
      "BAIXA": 0
    },
    "by_category": {
      "Estrutural": 1,
      "Categorias": 2,
      "Governança": 1,
      "Monitoramento": 1,
      "Documentação": 1
    },
    "by_timeline": {
      "immediate": 2,
      "short_term": 1,
      "medium_term": 2,
      "long_term": 1
    }
  },
  "recommendations": [
    {
      "category": "Estrutural",
      "priority": "CRÍTICA",
      "type": "orphan_categories",
      "title": "Resolver orphan_categories",
      "description": "9 categorias órfãs encontradas",
      "impact": "Categorias órfãs podem causar erros na criação de tickets",
      "effort": "Alto",
      "timeline": "Imediato (1-2 semanas)",
      "source": "Análise Estrutural"
    },
    {
      "category": "Categorias",
      "priority": "ALTA",
      "type": "orphan_categories",
      "title": "Corrigir 11 categorias órfãs",
      "description": "Identificadas 11 categorias órfãs que referenciam categorias pai inexistentes",
      "impact": "Pode causar erros na criação de tickets e inconsistências na estrutura",
      "effort": "Médio",
      "timeline": "Curto prazo (1-2 semanas)",
      "actions": [
        "Revisar categorias pai inexistentes",
        "Recriar categorias pai ou reatribuir categorias órfãs",
        "Validar integridade da hierarquia"
      ],
      "source": "Documentação de Categorias Órfãs"
    },
    {
      "category": "Governança",
      "priority": "ALTA",
      "type": "governance",
      "title": "Implementar governança de dados GLPI",
      "description": "Estabelecer processos e políticas para manutenção da qualidade dos dados",
      "impact": "Melhoria contínua da qualidade e consistência dos dados",
      "effort": "Alto",
      "timeline": "Longo prazo (2-3 meses)",
      "actions": [
        "Definir políticas de criação e manutenção de categorias",
        "Estabelecer processo de revisão periódica",
        "Criar documentação de padrões",
        "Implementar validações automáticas"
      ],
      "source": "Recomendação Geral"
    },
    {
      "category": "Monitoramento",
      "priority": "MÉDIA",
      "type": "monitoring",
      "title": "Implementar monitoramento contínuo",
      "description": "Criar sistema de monitoramento para detectar problemas estruturais automaticamente",
      "impact": "Detecção precoce de problemas e manutenção proativa",
      "effort": "Médio",
      "timeline": "Médio prazo (1-2 meses)",
      "actions": [
        "Automatizar análises estruturais",
        "Criar alertas para problemas críticos",
        "Implementar dashboards de qualidade",
        "Estabelecer métricas de qualidade"
      ],
      "source": "Recomendação Geral"
    },
    {
      "category": "Documentação",
      "priority": "MÉDIA",
      "type": "documentation",
      "title": "Melhorar documentação da estrutura",
      "description": "Criar e manter documentação atualizada da estrutura do GLPI",
      "impact": "Facilita manutenção e onboarding de novos usuários",
      "effort": "Médio",
      "timeline": "Médio prazo (3-4 semanas)",
      "actions": [
        "Documentar estrutura atual completa",
        "Criar guias de uso para cada componente",
        "Estabelecer processo de atualização da documentação",
        "Implementar versionamento da documentação"
      ],
      "source": "Recomendação Geral"
    },
    {
      "category": "Categorias",
      "priority": "MÉDIA",
      "type": "unused_categories",
      "title": "Revisar 6 categorias não utilizadas",
      "description": "Identificadas 6 categorias sem tickets associados",
      "impact": "Pode confundir usuários e tornar a interface mais complexa",
      "effort": "Baixo",
      "timeline": "Médio prazo (2-4 semanas)",
      "actions": [
        "Analisar necessidade de cada categoria não utilizada",
        "Remover categorias desnecessárias",
        "Consolidar categorias similares",
        "Implementar processo de governança"
      ],
      "source": "Documentação de Categorias Não Utilizadas"
    }
  ],
  "implementation_plan": {
    "phases": {
      "immediate": [
        {
          "category": "Estrutural",
          "priority": "CRÍTICA",
          "type": "orphan_categories",
          "title": "Resolver orphan_categories",
          "description": "9 categorias órfãs encontradas",
          "impact": "Categorias órfãs podem causar erros na criação de tickets",
          "effort": "Alto",
          "timeline": "Imediato (1-2 semanas)",
          "source": "Análise Estrutural"
        },
        {
          "category": "Categorias",
          "priority": "ALTA",
          "type": "orphan_categories",
          "title": "Corrigir 11 categorias órfãs",
          "description": "Identificadas 11 categorias órfãs que referenciam categorias pai inexistentes",
          "impact": "Pode causar erros na criação de tickets e inconsistências na estrutura",
          "effort": "Médio",
          "timeline": "Curto prazo (1-2 semanas)",
          "actions": [
            "Revisar categorias pai inexistentes",
            "Recriar categorias pai ou reatribuir categorias órfãs",
            "Validar integridade da hierarquia"
          ],
          "source": "Documentação de Categorias Órfãs"
        }
      ],
      "short_term": [
        {
          "category": "Categorias",
          "priority": "MÉDIA",
          "type": "unused_categories",
          "title": "Revisar 6 categorias não utilizadas",
          "description": "Identificadas 6 categorias sem tickets associados",
          "impact": "Pode confundir usuários e tornar a interface mais complexa",
          "effort": "Baixo",
          "timeline": "Médio prazo (2-4 semanas)",
          "actions": [
            "Analisar necessidade de cada categoria não utilizada",
            "Remover categorias desnecessárias",
            "Consolidar categorias similares",
            "Implementar processo de governança"
          ],
          "source": "Documentação de Categorias Não Utilizadas"
        }
      ],
      "medium_term": [
        {
          "category": "Monitoramento",
          "priority": "MÉDIA",
          "type": "monitoring",
          "title": "Implementar monitoramento contínuo",
          "description": "Criar sistema de monitoramento para detectar problemas estruturais automaticamente",
          "impact": "Detecção precoce de problemas e manutenção proativa",
          "effort": "Médio",
          "timeline": "Médio prazo (1-2 meses)",
          "actions": [
            "Automatizar análises estruturais",
            "Criar alertas para problemas críticos",
            "Implementar dashboards de qualidade",
            "Estabelecer métricas de qualidade"
          ],
          "source": "Recomendação Geral"
        },
        {
          "category": "Documentação",
          "priority": "MÉDIA",
          "type": "documentation",
          "title": "Melhorar documentação da estrutura",
          "description": "Criar e manter documentação atualizada da estrutura do GLPI",
          "impact": "Facilita manutenção e onboarding de novos usuários",
          "effort": "Médio",
          "timeline": "Médio prazo (3-4 semanas)",
          "actions": [
            "Documentar estrutura atual completa",
            "Criar guias de uso para cada componente",
            "Estabelecer processo de atualização da documentação",
            "Implementar versionamento da documentação"
          ],
          "source": "Recomendação Geral"
        }
      ],
      "long_term": [
        {
          "category": "Governança",
          "priority": "ALTA",
          "type": "governance",
          "title": "Implementar governança de dados GLPI",
          "description": "Estabelecer processos e políticas para manutenção da qualidade dos dados",
          "impact": "Melhoria contínua da qualidade e consistência dos dados",
          "effort": "Alto",
          "timeline": "Longo prazo (2-3 meses)",
          "actions": [
            "Definir políticas de criação e manutenção de categorias",
            "Estabelecer processo de revisão periódica",
            "Criar documentação de padrões",
            "Implementar validações automáticas"
          ],
          "source": "Recomendação Geral"
        }
      ]
    },
    "by_priority": {
      "CRÍTICA": [
        {
          "category": "Estrutural",
          "priority": "CRÍTICA",
          "type": "orphan_categories",
          "title": "Resolver orphan_categories",
          "description": "9 categorias órfãs encontradas",
          "impact": "Categorias órfãs podem causar erros na criação de tickets",
          "effort": "Alto",
          "timeline": "Imediato (1-2 semanas)",
          "source": "Análise Estrutural"
        }
      ],
      "ALTA": [
        {
          "category": "Categorias",
          "priority": "ALTA",
          "type": "orphan_categories",
          "title": "Corrigir 11 categorias órfãs",
          "description": "Identificadas 11 categorias órfãs que referenciam categorias pai inexistentes",
          "impact": "Pode causar erros na criação de tickets e inconsistências na estrutura",
          "effort": "Médio",
          "timeline": "Curto prazo (1-2 semanas)",
          "actions": [
            "Revisar categorias pai inexistentes",
            "Recriar categorias pai ou reatribuir categorias órfãs",
            "Validar integridade da hierarquia"
          ],
          "source": "Documentação de Categorias Órfãs"
        },
        {
          "category": "Governança",
          "priority": "ALTA",
          "type": "governance",
          "title": "Implementar governança de dados GLPI",
          "description": "Estabelecer processos e políticas para manutenção da qualidade dos dados",
          "impact": "Melhoria contínua da qualidade e consistência dos dados",
          "effort": "Alto",
          "timeline": "Longo prazo (2-3 meses)",
          "actions": [
            "Definir políticas de criação e manutenção de categorias",
            "Estabelecer processo de revisão periódica",
            "Criar documentação de padrões",
            "Implementar validações automáticas"
          ],
          "source": "Recomendação Geral"
        }
      ],
      "MÉDIA": [
        {
          "category": "Monitoramento",
          "priority": "MÉDIA",
          "type": "monitoring",
          "title": "Implementar monitoramento contínuo",
          "description": "Criar sistema de monitoramento para detectar problemas estruturais automaticamente",
          "impact": "Detecção precoce de problemas e manutenção proativa",
          "effort": "Médio",
          "timeline": "Médio prazo (1-2 meses)",
          "actions": [
            "Automatizar análises estruturais",
            "Criar alertas para problemas críticos",
            "Implementar dashboards de qualidade",
            "Estabelecer métricas de qualidade"
          ],
          "source": "Recomendação Geral"
        },
        {
          "category": "Documentação",
          "priority": "MÉDIA",
          "type": "documentation",
          "title": "Melhorar documentação da estrutura",
          "description": "Criar e manter documentação atualizada da estrutura do GLPI",
          "impact": "Facilita manutenção e onboarding de novos usuários",
          "effort": "Médio",
          "timeline": "Médio prazo (3-4 semanas)",
          "actions": [
            "Documentar estrutura atual completa",
            "Criar guias de uso para cada componente",
            "Estabelecer processo de atualização da documentação",
            "Implementar versionamento da documentação"
          ],
          "source": "Recomendação Geral"
        },
        {
          "category": "Categorias",
          "priority": "MÉDIA",
          "type": "unused_categories",
          "title": "Revisar 6 categorias não utilizadas",
          "description": "Identificadas 6 categorias sem tickets associados",
          "impact": "Pode confundir usuários e tornar a interface mais complexa",
          "effort": "Baixo",
          "timeline": "Médio prazo (2-4 semanas)",
          "actions": [
            "Analisar necessidade de cada categoria não utilizada",
            "Remover categorias desnecessárias",
            "Consolidar categorias similares",
            "Implementar processo de governança"
          ],
          "source": "Documentação de Categorias Não Utilizadas"
        }
      ],
      "BAIXA": []
    },
    "by_category": {
      "Estrutural": [
        {
          "category": "Estrutural",
          "priority": "CRÍTICA",
          "type": "orphan_categories",
          "title": "Resolver orphan_categories",
          "description": "9 categorias órfãs encontradas",
          "impact": "Categorias órfãs podem causar erros na criação de tickets",
          "effort": "Alto",
          "timeline": "Imediato (1-2 semanas)",
          "source": "Análise Estrutural"
        }
      ],
      "Categorias": [
        {
          "category": "Categorias",
          "priority": "ALTA",
          "type": "orphan_categories",
          "title": "Corrigir 11 categorias órfãs",
          "description": "Identificadas 11 categorias órfãs que referenciam categorias pai inexistentes",
          "impact": "Pode causar erros na criação de tickets e inconsistências na estrutura",
          "effort": "Médio",
          "timeline": "Curto prazo (1-2 semanas)",
          "actions": [
            "Revisar categorias pai inexistentes",
            "Recriar categorias pai ou reatribuir categorias órfãs",
            "Validar integridade da hierarquia"
          ],
          "source": "Documentação de Categorias Órfãs"
        },
        {
          "category": "Categorias",
          "priority": "MÉDIA",
          "type": "unused_categories",
          "title": "Revisar 6 categorias não utilizadas",
          "description": "Identificadas 6 categorias sem tickets associados",
          "impact": "Pode confundir usuários e tornar a interface mais complexa",
          "effort": "Baixo",
          "timeline": "Médio prazo (2-4 semanas)",
          "actions": [
            "Analisar necessidade de cada categoria não utilizada",
            "Remover categorias desnecessárias",
            "Consolidar categorias similares",
            "Implementar processo de governança"
          ],
          "source": "Documentação de Categorias Não Utilizadas"
        }
      ],
      "Governança": [
        {
          "category": "Governança",
          "priority": "ALTA",
          "type": "governance",
          "title": "Implementar governança de dados GLPI",
          "description": "Estabelecer processos e políticas para manutenção da qualidade dos dados",
          "impact": "Melhoria contínua da qualidade e consistência dos dados",
          "effort": "Alto",
          "timeline": "Longo prazo (2-3 meses)",
          "actions": [
            "Definir políticas de criação e manutenção de categorias",
            "Estabelecer processo de revisão periódica",
            "Criar documentação de padrões",
            "Implementar validações automáticas"
          ],
          "source": "Recomendação Geral"
        }
      ],
      "Monitoramento": [
        {
          "category": "Monitoramento",
          "priority": "MÉDIA",
          "type": "monitoring",
          "title": "Implementar monitoramento contínuo",
          "description": "Criar sistema de monitoramento para detectar problemas estruturais automaticamente",
          "impact": "Detecção precoce de problemas e manutenção proativa",
          "effort": "Médio",
          "timeline": "Médio prazo (1-2 meses)",
          "actions": [
            "Automatizar análises estruturais",
            "Criar alertas para problemas críticos",
            "Implementar dashboards de qualidade",
            "Estabelecer métricas de qualidade"
          ],
          "source": "Recomendação Geral"
        }
      ],
      "Documentação": [
        {
          "category": "Documentação",
          "priority": "MÉDIA",
          "type": "documentation",
          "title": "Melhorar documentação da estrutura",
          "description": "Criar e manter documentação atualizada da estrutura do GLPI",
          "impact": "Facilita manutenção e onboarding de novos usuários",
          "effort": "Médio",
          "timeline": "Médio prazo (3-4 semanas)",
          "actions": [
            "Documentar estrutura atual completa",
            "Criar guias de uso para cada componente",
            "Estabelecer processo de atualização da documentação",
            "Implementar versionamento da documentação"
          ],
          "source": "Recomendação Geral"
        }
      ]
    }
  }
}